{
  "version": "1.0",
  "chainId": "1",
  "createdAt": 1688559620808,
  "meta": {
    "name": "Transactions Batch",
    "description": "enableRecoveryMode for affected Pools",
    "txBuilderVersion": "1.16.0",
    "createdFromSafeAddress": "",
    "createdFromOwnerAddress": ""
  },
  "createdFromSafeAddress": "0xA29F61256e948F3FB707b4b3B138C5cCb9EF9888",
  "transactions": [
    {
      "to": "0x0d05Aac44aC7Dd3c7ba5d50Be93EB884A057d234",
      "value": "0",
      "data": null,
      "contractMethod": {
        "inputs": [],
        "name": "enableRecoveryMode",
        "payable": false
      },
      "contractInputsValues": null
    },
    {
      "to": "0x0DA692Ac0611397027c91E559cFD482C4197e403",
      "value": "0",
      "data": null,
      "contractMethod": {
        "inputs": [],
        "name": "enableRecoveryMode",
        "payable": false
      },
      "contractInputsValues": null
    },
    {
      "to": "0x11839D635e2F0270DA37e8ef4324D4d5d5432957",
      "value": "0",
      "data": null,
      "contractMethod": {
        "inputs": [],
        "name": "enableRecoveryMode",
        "payable": false
      },
      "contractInputsValues": null
    },
    {
      "to": "0x1bd2F176a812e312077BcA87e37c08432Bb09F3e",
      "value": "0",
      "data": null,
      "contractMethod": {
        "inputs": [],
        "name": "enableRecoveryMode",
        "payable": false
      },
      "contractInputsValues": null
    },
    {
      "to": "0x26c2B83FC8535DeEaD276f5Cc3ad9c1a2192E027",
      "value": "0",
      "data": null,
      "contractMethod": {
        "inputs": [],
        "name": "enableRecoveryMode",
        "payable": false
      },
      "contractInputsValues": null
    },
    {
      "to": "0x2B218683178d029BAB6c9789b1073aA6c96E5176",
      "value": "0",
      "data": null,
      "contractMethod": {
        "inputs": [],
        "name": "enableRecoveryMode",
        "payable": false
      },
      "contractInputsValues": null
    },
    {
      "to": "0x2e52c64FD319E380cDbCFC4577eA1Fda558a32e4",
      "value": "0",
      "data": null,
      "contractMethod": {
        "inputs": [],
        "name": "enableRecoveryMode",
        "payable": false
      },
      "contractInputsValues": null
    },
    {
      "to": "0x2F4eb100552ef93840d5aDC30560E5513DFfFACb",
      "value": "0",
      "data": null,
      "contractMethod": {
        "inputs": [],
        "name": "enableRecoveryMode",
        "payable": false
      },
      "contractInputsValues": null
    },
    {
      "to": "0x3035917bE42aF437CBdD774Be26B9EC90a2BD677",
      "value": "0",
      "data": null,
      "contractMethod": {
        "inputs": [],
        "name": "enableRecoveryMode",
        "payable": false
      },
      "contractInputsValues": null
    },
    {
      "to": "0x3CdAE4f12A67ba563499e102f309c73213cB241c",
      "value": "0",
      "data": null,
      "contractMethod": {
        "inputs": [],
        "name": "enableRecoveryMode",
        "payable": false
      },
      "contractInputsValues": null
    },
    {
      "to": "0x3f7a7fd7F214bE45EC26820Fd01aC3bE4fC75aa7",
      "value": "0",
      "data": null,
      "contractMethod": {
        "inputs": [],
        "name": "enableRecoveryMode",
        "payable": false
      },
      "contractInputsValues": null
    },
    {
      "to": "0x3fCb7085B8F2F473F80bF6D879cAe99eA4DE9344",
      "value": "0",
      "data": null,
      "contractMethod": {
        "inputs": [],
        "name": "enableRecoveryMode",
        "payable": false
      },
      "contractInputsValues": null
    },
    {
      "to": "0x41503C9D499ddbd1dCdf818a1b05e9774203Bf46",
      "value": "0",
      "data": null,
      "contractMethod": {
        "inputs": [],
        "name": "enableRecoveryMode",
        "payable": false
      },
      "contractInputsValues": null
    },
    {
      "to": "0x4228290eE9cab692938Ff0b4ba303FBCDB68e9F2",
      "value": "0",
      "data": null,
      "contractMethod": {
        "inputs": [],
        "name": "enableRecoveryMode",
        "payable": false
      },
      "contractInputsValues": null
    },
    {
      "to": "0x454Ed96955d04D2f5cDD05E0Fd1C77975bFE5307",
      "value": "0",
      "data": null,
      "contractMethod": {
        "inputs": [],
        "name": "enableRecoveryMode",
        "payable": false
      },
      "contractInputsValues": null
    },
    {
      "to": "0x4C81255Cc9eD7062180ea99962fE05aC0D57350B",
      "value": "0",
      "data": null,
      "contractMethod": {
        "inputs": [],
        "name": "enableRecoveryMode",
        "payable": false
      },
      "contractInputsValues": null
    },
    {
      "to": "0x4CbdE5C4B4B53EBE4aF4adB85404725985406163",
      "value": "0",
      "data": null,
      "contractMethod": {
        "inputs": [],
        "name": "enableRecoveryMode",
        "payable": false
      },
      "contractInputsValues": null
    },
    {
      "to": "0x4cE277Df0FeB5B4d07a0ca2ADCf5326E4005239d",
      "value": "0",
      "data": null,
      "contractMethod": {
        "inputs": [],
        "name": "enableRecoveryMode",
        "payable": false
      },
      "contractInputsValues": null
    },
    {
      "to": "0x639883476960a23b38579acfd7D71561A0f408Cf",
      "value": "0",
      "data": null,
      "contractMethod": {
        "inputs": [],
        "name": "enableRecoveryMode",
        "payable": false
      },
      "contractInputsValues": null
    },
    {
      "to": "0x6a1eB2e9B45e772F55bd9a34659A04B6F75Da687",
      "value": "0",
      "data": null,
      "contractMethod": {
        "inputs": [],
        "name": "enableRecoveryMode",
        "payable": false
      },
      "contractInputsValues": null
    },
    {
      "to": "0x6C56E72c551B5aC4Bf54A620A76077cA768C8FE4",
      "value": "0",
      "data": null,
      "contractMethod": {
        "inputs": [],
        "name": "enableRecoveryMode",
        "payable": false
      },
      "contractInputsValues": null
    },
    {
      "to": "0x74CBfAF94A3577c539a9dCEE9870A6349a33b34f",
      "value": "0",
      "data": null,
      "contractMethod": {
        "inputs": [],
        "name": "enableRecoveryMode",
        "payable": false
      },
      "contractInputsValues": null
    },
    {
      "to": "0x813E3fE1761f714c502d1d2d3a7CCEB33f37F59D",
      "value": "0",
      "data": null,
      "contractMethod": {
        "inputs": [],
        "name": "enableRecoveryMode",
        "payable": false
      },
      "contractInputsValues": null
    },
    {
      "to": "0x82698aeCc9E28e9Bb27608Bd52cF57f704BD1B83",
      "value": "0",
      "data": null,
      "contractMethod": {
        "inputs": [],
        "name": "enableRecoveryMode",
        "payable": false
      },
      "contractInputsValues": null
    },
    {
      "to": "0x9516a2d25958EdB8da246a320f2c7d94A0DBe25d",
      "value": "0",
      "data": null,
      "contractMethod": {
        "inputs": [],
        "name": "enableRecoveryMode",
        "payable": false
      },
      "contractInputsValues": null
    },
    {
      "to": "0x959216BB492B2efa72b15B7AAcEa5B5C984c3ccA",
      "value": "0",
      "data": null,
      "contractMethod": {
        "inputs": [],
        "name": "enableRecoveryMode",
        "payable": false
      },
      "contractInputsValues": null
    },
    {
      "to": "0x9B692f571b256140a39a34676BffA30634c586e1",
      "value": "0",
      "data": null,
      "contractMethod": {
        "inputs": [],
        "name": "enableRecoveryMode",
        "payable": false
      },
      "contractInputsValues": null
    },
    {
      "to": "0x9d7f992c900FbeA0EC314Bdd71b7cC1becF76A33",
      "value": "0",
      "data": null,
      "contractMethod": {
        "inputs": [],
        "name": "enableRecoveryMode",
        "payable": false
      },
      "contractInputsValues": null
    },
    {
      "to": "0xAC5B4EF7eDe2F2843a704E96dcAA637F4BA3Dc3f",
      "value": "0",
      "data": null,
      "contractMethod": {
        "inputs": [],
        "name": "enableRecoveryMode",
        "payable": false
      },
      "contractInputsValues": null
    },
    {
      "to": "0xae37D54Ae477268B9997d4161B96b8200755935c",
      "value": "0",
      "data": null,
      "contractMethod": {
        "inputs": [],
        "name": "enableRecoveryMode",
        "payable": false
      },
      "contractInputsValues": null
    },
    {
      "to": "0xaE8535c23afeDdA9304B03c68a3563B75fc8f92b",
      "value": "0",
      "data": null,
      "contractMethod": {
        "inputs": [],
        "name": "enableRecoveryMode",
        "payable": false
      },
      "contractInputsValues": null
    },
    {
      "to": "0xB841B062eA8CCf5C4cb78032e91dE4aE87556042",
      "value": "0",
      "data": null,
      "contractMethod": {
        "inputs": [],
        "name": "enableRecoveryMode",
        "payable": false
      },
      "contractInputsValues": null
    },
    {
      "to": "0xbB6881874825E60e1160416D6C426eae65f2459E",
      "value": "0",
      "data": null,
      "contractMethod": {
        "inputs": [],
        "name": "enableRecoveryMode",
        "payable": false
      },
      "contractInputsValues": null
    },
    {
      "to": "0xbF2ef8bDC2fC0F3203B3a01778E3ec5009AEEf33",
      "value": "0",
      "data": null,
      "contractMethod": {
        "inputs": [],
        "name": "enableRecoveryMode",
        "payable": false
      },
      "contractInputsValues": null
    },
    {
      "to": "0xc2B021133D1b0cF07dba696fd5DD89338428225B",
      "value": "0",
      "data": null,
      "contractMethod": {
        "inputs": [],
        "name": "enableRecoveryMode",
        "payable": false
      },
      "contractInputsValues": null
    },
    {
      "to": "0xc443C15033FCB6Cf72cC24f1BDA0Db070DdD9786",
      "value": "0",
      "data": null,
      "contractMethod": {
        "inputs": [],
        "name": "enableRecoveryMode",
        "payable": false
      },
      "contractInputsValues": null
    },
    {
      "to": "0xc50d4347209F285247BDa8A09Fc1C12CE42031c3",
      "value": "0",
      "data": null,
      "contractMethod": {
        "inputs": [],
        "name": "enableRecoveryMode",
        "payable": false
      },
      "contractInputsValues": null
    },
    {
      "to": "0xcfAE6E251369467F465f13836Ac8135bd42f8A56",
      "value": "0",
      "data": null,
      "contractMethod": {
        "inputs": [],
        "name": "enableRecoveryMode",
        "payable": false
      },
      "contractInputsValues": null
    },
    {
      "to": "0xd7edb56F63b2a0191742aEa32DF1F98ca81ed9c6",
      "value": "0",
      "data": null,
      "contractMethod": {
        "inputs": [],
        "name": "enableRecoveryMode",
        "payable": false
      },
      "contractInputsValues": null
    },
    {
      "to": "0xE2D16b0A39F3FBb4389a0E8F1efCBecFB3d1E6E1",
      "value": "0",
      "data": null,
      "contractMethod": {
        "inputs": [],
        "name": "enableRecoveryMode",
        "payable": false
      },
      "contractInputsValues": null
    },
    {
      "to": "0xE8C56405Bc405840154d9b572927F4197D110dE1",
      "value": "0",
      "data": null,
      "contractMethod": {
        "inputs": [],
        "name": "enableRecoveryMode",
        "payable": false
      },
      "contractInputsValues": null
    },
    {
      "to": "0xfa24A90A3F2bBE5FEEA92B95cD0d14Ce709649f9",
      "value": "0",
      "data": null,
      "contractMethod": {
        "inputs": [],
        "name": "enableRecoveryMode",
        "payable": false
      },
      "contractInputsValues": null
    }
  ]
}
