{
  "version": "1.0",
  "chainId": "1",
  "createdAt": 1681321880536,
  "meta": {
    "name": "Transactions Batch",
    "description": "",
    "txBuilderVersion": "1.13.3",
    "createdFromSafeAddress": "0x4D6175d58C5AceEf30F546C0d5A557efFa53A950",
    "createdFromOwnerAddress": "",
    "checksum": "0xd2d40233494806c3d91ca24493c91ee62ca69c36605b0738eae83d7cf012ca7c"
  },
  "transactions": [
    {
      "to": "0xBA12222222228d8Ba445958a75a0704d566BF2C8",
      "value": "0",
      "data": "",
      "contractMethod": null,
      "contractInputsValues": null
    }
  ]
}