{
  "morpho": {
    "1": {
      "0x58D97B57BB95320F9a05dC918Aef65434969c2B2": {
        "claimable": "5277078421977622778862",
        "pools": {
          "pxETH-gtWETHe": {
            "address": "0x5512fdDC40842b257e2A7742Be3DaDcf31574d53",
            "reward_wei": "413575318047475558339"
          },
          "steakUSDTlite-steakUSDR-steakUSDQ": {
            "address": "0xf028Ac624074D6793C36dc8A06ECeC0F5a39a718",
            "reward_wei": "741110430491662562717"
          },
          "csUSDC-csUSDT": {
            "address": "0x10A04efbA5B880e169920Fd4348527C64FB29d4D",
            "reward_wei": "4122392673438484657804"
          }
        }
      }
    },
    "8453": {
      "0xBAa5CC21fd487B8Fcc2F632f3F4E8D37262a0842": {
        "claimable": "",
        "pools": {
          "sUSDS-smUSDC": {
            "address": "0x4147D8AeECb75bc9f5c973c3B73D2dfC4DCCe131",
            "reward_wei": "141059927273665511826"
          }
        }
      },
      "0x1c7a460413dd4e964f96d8dfc56e7223ce88cd85": {
        "claimable": "",
        "pools": {
          "sUSDS-smUSDC": {
            "address": "0x4147D8AeECb75bc9f5c973c3B73D2dfC4DCCe131",
            "reward_wei": "588892905376647377835"
          }
        }
      }
    }
  },
  "aave": {
    "1": {
      "reward_token": "0x030bA81f1c18d280636F32af80b9AAd02Cf0854e",
      "pools": {
        "waEthLidoWETH-waEthLidowstETH": {
          "address": "0xc4Ce391d82D164c166dF9c8336DDF84206b2F812",
          "reward_wei": "5000000000000000000"
        }
      }
    }
  }
}
