{"version":"1.0","chainId":"100","createdAt":1746039587176,"meta":{"name":"Transactions Batch","description":"Set swap fee to 0.25% for Balancer EURe/sDAI","createdFromSafeAddress":"0x14969B55a675d13a1700F71A37511bc22D90155a"},"transactions":[{"to":"0xdd439304a77f54b1f7854751ac1169b279591ef7","value":"0","data":null,"contractMethod":{"inputs":[{"name":"swapFeePercentage","type":"uint256","internalType":"uint256"}],"name":"setSwapFeePercentage","payable":false},"contractInputsValues":{"swapFeePercentage":"2500000000000000"}}]}